[
  {
    "LocationID": "VN7011101",
    "LocationName": "Phường 01"
  },
  {
    "LocationID": "VN7011103",
    "LocationName": "Phường 02"
  },
  {
    "LocationID": "VN7011105",
    "LocationName": "Phường 03"
  },
  {
    "LocationID": "VN7011107",
    "LocationName": "Phường 04"
  },
  {
    "LocationID": "VN7011109",
    "LocationName": "Phường 05"
  },
  {
    "LocationID": "VN7011111",
    "LocationName": "Phường 06"
  },
  {
    "LocationID": "VN7011113",
    "LocationName": "Phường 07"
  },
  {
    "LocationID": "VN7011115",
    "LocationName": "Phường 08"
  },
  {
    "LocationID": "VN7011117",
    "LocationName": "Phường 09"
  },
  {
    "LocationID": "VN7011119",
    "LocationName": "Phường 10"
  },
  {
    "LocationID": "VN7011121",
    "LocationName": "Phường 11"
  },
  {
    "LocationID": "VN7011123",
    "LocationName": "Phường 12"
  },
  {
    "LocationID": "VN7011125",
    "LocationName": "Phường 13"
  },
  {
    "LocationID": "VN7011127",
    "LocationName": "Phường 14"
  }
]