[
  {
    "LocationID": "VN5071907",
    "LocationName": "Thị trấn Diêu Trì"
  },
  {
    "LocationID": "VN5071909",
    "LocationName": "Thị trấn Tuy Phước"
  },
  {
    "LocationID": "VN5071923",
    "LocationName": "Xã Phước An"
  },
  {
    "LocationID": "VN5071919",
    "LocationName": "Xã Phước Hiệp"
  },
  {
    "LocationID": "VN5071917",
    "LocationName": "Xã Phước Hòa"
  },
  {
    "LocationID": "VN5071913",
    "LocationName": "Xã Phước Hưng"
  },
  {
    "LocationID": "VN5071921",
    "LocationName": "Xã Phước Lộc"
  },
  {
    "LocationID": "VN5071901",
    "LocationName": "Xã Phước Nghĩa"
  },
  {
    "LocationID": "VN5071915",
    "LocationName": "Xã Phước Quang"
  },
  {
    "LocationID": "VN5071905",
    "LocationName": "Xã Phước Sơn"
  },
  {
    "LocationID": "VN5071911",
    "LocationName": "Xã Phước Thắng"
  },
  {
    "LocationID": "VN5071925",
    "LocationName": "Xã Phước Thành"
  },
  {
    "LocationID": "VN5071903",
    "LocationName": "Xã Phước Thuận"
  }
]