[
  {
    "LocationID": "VN8160907",
    "LocationName": "Thị trấn Nàng Mau"
  },
  {
    "LocationID": "VN8160919",
    "LocationName": "Xã Vị Bình"
  },
  {
    "LocationID": "VN8160905",
    "LocationName": "Xã Vị Đông"
  },
  {
    "LocationID": "VN8160903",
    "LocationName": "Xã Vị Thắng"
  },
  {
    "LocationID": "VN8160901",
    "LocationName": "Xã Vị Thanh"
  },
  {
    "LocationID": "VN8160911",
    "LocationName": "Xã Vị Thuỷ"
  },
  {
    "LocationID": "VN8160909",
    "LocationName": "Xã Vị Trung"
  },
  {
    "LocationID": "VN8160913",
    "LocationName": "Xã Vĩnh Thuận Tây"
  },
  {
    "LocationID": "VN8160915",
    "LocationName": "Xã Vĩnh Trung"
  },
  {
    "LocationID": "VN8160917",
    "LocationName": "Xã Vĩnh Tường"
  }
]