[
  {
    "LocationID": "VN5030903",
    "LocationName": "Thị trấn Vĩnh Điện"
  },
  {
    "LocationID": "VN5030925",
    "LocationName": "Xã Điện An"
  },
  {
    "LocationID": "VN5030931",
    "LocationName": "Xã Điện Dương"
  },
  {
    "LocationID": "VN5030913",
    "LocationName": "Xã Điện Hòa"
  },
  {
    "LocationID": "VN5030905",
    "LocationName": "Xã Điện Hồng"
  },
  {
    "LocationID": "VN5030937",
    "LocationName": "Xã Điện Minh"
  },
  {
    "LocationID": "VN5030907",
    "LocationName": "Xã Điện Nam Bắc"
  },
  {
    "LocationID": "VN5030929",
    "LocationName": "Xã Điện Nam Đông"
  },
  {
    "LocationID": "VN5030927",
    "LocationName": "Xã Điện Nam Trung"
  },
  {
    "LocationID": "VN5030921",
    "LocationName": "Xã Điện Ngọc"
  },
  {
    "LocationID": "VN5030909",
    "LocationName": "Xã Điện Phong"
  },
  {
    "LocationID": "VN5030901",
    "LocationName": "Xã Điện Phước"
  },
  {
    "LocationID": "VN5030939",
    "LocationName": "Xã Điện Phương"
  },
  {
    "LocationID": "VN5030933",
    "LocationName": "Xã Điện Quang"
  },
  {
    "LocationID": "VN5030915",
    "LocationName": "Xã Điện Thắng Bắc"
  },
  {
    "LocationID": "VN5030919",
    "LocationName": "Xã Điện Thắng Nam"
  },
  {
    "LocationID": "VN5030917",
    "LocationName": "Xã Điện Thắng Trung"
  },
  {
    "LocationID": "VN5030923",
    "LocationName": "Xã Điện Thọ"
  },
  {
    "LocationID": "VN5030911",
    "LocationName": "Xã Điện Tiến"
  },
  {
    "LocationID": "VN5030935",
    "LocationName": "Xã Điện Trung"
  }
]