[
  {
    "LocationID": "VN1012723",
    "LocationName": "Phường Biên Giang"
  },
  {
    "LocationID": "VN1012721",
    "LocationName": "Phường Đồng Mai"
  },
  {
    "LocationID": "VN1012719",
    "LocationName": "Phường Dương Nội"
  },
  {
    "LocationID": "VN1012711",
    "LocationName": "Phường Hà Cầu"
  },
  {
    "LocationID": "VN1012715",
    "LocationName": "Phường Kiến Hưng"
  },
  {
    "LocationID": "VN1012728",
    "LocationName": "Phường La Khê"
  },
  {
    "LocationID": "VN1012703",
    "LocationName": "Phường Mộ Lao"
  },
  {
    "LocationID": "VN1012701",
    "LocationName": "Phường Nguyễn Trãi"
  },
  {
    "LocationID": "VN1012727",
    "LocationName": "Phường Phú La"
  },
  {
    "LocationID": "VN1012717",
    "LocationName": "Phường Phú Lãm"
  },
  {
    "LocationID": "VN1012725",
    "LocationName": "Phường Phú Lương"
  },
  {
    "LocationID": "VN1012709",
    "LocationName": "Phường Phúc La"
  },
  {
    "LocationID": "VN1012707",
    "LocationName": "Phường Quang Trung"
  },
  {
    "LocationID": "VN1012705",
    "LocationName": "Phường Vạn Phúc"
  },
  {
    "LocationID": "VN1012704",
    "LocationName": "Phường Văn Quán"
  },
  {
    "LocationID": "VN1012713",
    "LocationName": "Phường Yên Nghĩa"
  },
  {
    "LocationID": "VN1012729",
    "LocationName": "Phường Yết Kiêu"
  }
]