[
  {
    "LocationID": "VN6031307",
    "LocationName": "Thị trấn Kông Chro"
  },
  {
    "LocationID": "VN6031311",
    "LocationName": "Xã An Trung"
  },
  {
    "LocationID": "VN6031319",
    "LocationName": "Xã Chơ Long"
  },
  {
    "LocationID": "VN6031309",
    "LocationName": "Xã Chư Krêy"
  },
  {
    "LocationID": "VN6031325",
    "LocationName": "Xã Đăk Kơ Ning"
  },
  {
    "LocationID": "VN6031323",
    "LocationName": "Xã Đăk Pling"
  },
  {
    "LocationID": "VN6031327",
    "LocationName": "Xã Đăk Pơ Pho"
  },
  {
    "LocationID": "VN6031317",
    "LocationName": "Xã Đăk Song"
  },
  {
    "LocationID": "VN6031313",
    "LocationName": "Xã Đăk Tơ Pang"
  },
  {
    "LocationID": "VN6031303",
    "LocationName": "Xã Kông Yang"
  },
  {
    "LocationID": "VN6031315",
    "LocationName": "Xã SRó"
  },
  {
    "LocationID": "VN6031301",
    "LocationName": "Xã Ya Ma"
  },
  {
    "LocationID": "VN6031321",
    "LocationName": "Xã Yang Nam"
  },
  {
    "LocationID": "VN6031305",
    "LocationName": "Xã Yang Trung"
  }
]